LICENSE
MANIFEST.in
README.txt
setup.py
src/RandomLibrary/__init__.py
src/RandomLibrary/keywords.py
src/robotframework_randomlibrary.egg-info/PKG-INFO
src/robotframework_randomlibrary.egg-info/SOURCES.txt
src/robotframework_randomlibrary.egg-info/dependency_links.txt
src/robotframework_randomlibrary.egg-info/not-zip-safe
src/robotframework_randomlibrary.egg-info/requires.txt
src/robotframework_randomlibrary.egg-info/top_level.txt
utilities/jenkins.sh