Metadata-Version: 1.0
Name: robotframework-randomlibrary
Version: 0.0.1
Summary: A collection of random utilities that can be used within tests written using RobotFramework
Home-page: https://github.com/svyzz/robotframework-random
Author: Arun Venkatram
Author-email: stuxnetting@gmail.com
License: Apache 2.0, see LICENSE.txt
Keywords: robotframework automation arun
Platform: any
